LICENSE
README.md
setup.py
FetchRepository/FetchRepo.py
FetchRepository/__init__.py
fetch_my_repo.egg-info/PKG-INFO
fetch_my_repo.egg-info/SOURCES.txt
fetch_my_repo.egg-info/dependency_links.txt
fetch_my_repo.egg-info/top_level.txt