Metadata-Version: 2.1
Name: fetch-my-repo
Version: 0.1.0
Summary: Passing your GitHub https url, It fetches your content from GitHub repo
Author: Al-Fareed
License-File: LICENSE
